colorio/__about__.py
colorio/__init__.py
colorio/_exceptions.py
colorio/_helpers.py
colorio/_license_validation.py
colorio/_rgb_gamut.py
colorio/_surface_gamut.py
colorio/_tools.py
colorio/_visible_gamut.py
colorio/py.typed
colorio/cat/__init__.py
colorio/cat/bianco_schettini.py
colorio/cat/bradford.py
colorio/cat/cat02.py
colorio/cat/cat16.py
colorio/cat/cmccat2000.py
colorio/cat/sharp.py
colorio/cat/von_kries.py
colorio/cs/__init__.py
colorio/cs/_cam16.py
colorio/cs/_ciecam02.py
colorio/cs/_ciehcl.py
colorio/cs/_cielab.py
colorio/cs/_cielch.py
colorio/cs/_cieluv.py
colorio/cs/_color_coordinates.py
colorio/cs/_color_space.py
colorio/cs/_din99.py
colorio/cs/_hdr.py
colorio/cs/_helpers.py
colorio/cs/_hsl.py
colorio/cs/_hsv.py
colorio/cs/_ictcp.py
colorio/cs/_igpgtg.py
colorio/cs/_ipt.py
colorio/cs/_jzazbz.py
colorio/cs/_lch.py
colorio/cs/_oklab.py
colorio/cs/_oklch.py
colorio/cs/_osa_ucs.py
colorio/cs/_prolab.py
colorio/cs/_rlab.py
colorio/cs/_srgb.py
colorio/cs/_srlab2.py
colorio/cs/_xyy.py
colorio/cs/_xyz.py
colorio/data/__init__.py
colorio/data/color_distance.py
colorio/data/ellipse.py
colorio/data/helpers.py
colorio/data/hue_linearity.py
colorio/data/bfd_p/__init__.py
colorio/data/bfd_p/bfd-c.json
colorio/data/bfd_p/bfd-d65.json
colorio/data/bfd_p/bfd-m.json
colorio/data/combvd/__init__.py
colorio/data/ebner_fairchild/__init__.py
colorio/data/ebner_fairchild/ebner_fairchild.json
colorio/data/fairchild_chen/__init__.py
colorio/data/fairchild_chen/fairchild_chen.json
colorio/data/hung_berns/__init__.py
colorio/data/hung_berns/hb-table1.json
colorio/data/hung_berns/hb-table2.json
colorio/data/hung_berns/hb-table3.json
colorio/data/hung_berns/hb-table4.json
colorio/data/leeds/__init__.py
colorio/data/leeds/leeds.json
colorio/data/luo_rigg/__init__.py
colorio/data/luo_rigg/luo-rigg.json
colorio/data/macadam_1942/__init__.py
colorio/data/macadam_1942/m42-table1.json
colorio/data/macadam_1942/m42-table2.json
colorio/data/macadam_1942/m42-table3.json
colorio-0.12.18.dist-info/METADATA
colorio-0.12.18.dist-info/WHEEL
colorio-0.12.18.dist-info/top_level.txt
colorio-0.12.18.dist-info/RECORD
